fkscore/__init__.py
fkscore/fkscore.py
fkscore-2.0.1.dist-info/LICENSE
fkscore-2.0.1.dist-info/METADATA
fkscore-2.0.1.dist-info/WHEEL
fkscore-2.0.1.dist-info/top_level.txt
fkscore-2.0.1.dist-info/RECORD
